a1/a1/Question 2/q2.v
/*
	Name: Vybhav Pai (17CO252)
	Name: Shrinidhi Anil Varna (17CO145)
*/


module instruction_memory(clk,PC,reset,inst);
input wire clk; // variable that stores clock signal
output reg [31:0] PC; // updated value of PC
output reg [31:0] inst; // instruction to be fetched
input reset;
reg [7:0] inst_mem[4194304:268435456];

integer i;
initial 
	begin
		for(i=4194304;i<268435456;i++)
		begin
			inst_mem[i] = 8'b0;
		end
	PC <= 4194304;
	end

always @(posedge clk) begin
	if(reset) 
	begin
		PC = 4194304;						// resetting PC to its original value
	end

	inst[7:0] <= inst_mem[PC];
	inst[15:8] <= inst_mem[PC+1];
	inst[23:16] <= inst_mem[PC+2];
	inst[31:24] <= inst_mem[PC+3];
	
	
	PC <= PC + 32'b100;						// incrementing PC value
	
	end

endmodule

Assignment 1/a1/Question 2/q2_tb.v
/*
	Name: Vybhav Pai (17CO252)
	Name: Shrinidhi Anil Varna (17CO145)
*/


`include "q2.v"

module q2_tb;

//reg [31:0] PC; // program counter value
reg clk; // variable that stores clock signal
wire [31:0] PC; // updated value of PC
wire [31:0] inst; // instruction to be fetched
reg reset;
initial
begin
	clk = 1'b0;
	repeat(200)
		#1 clk = ~clk;
end

instruction_memory M(clk,PC,reset,inst);
initial
	begin
		$dumpfile("q2.vcd");
		$dumpvars(0,q2_tb);
		reset = 1'b0;
		#3 $display("%g Instruction fetched = %b and nPC = %b",$time,inst,PC);
		
		#2 $display("%g Instruction fetched = %b and nPC = %b",$time,inst,PC);
		 reset = 1'b1;
		#2 $display("%g Instruction fetched = %b and nPC = %b",$time,inst,PC);
		 reset = 1'b0;
		#2 $display("%g Instruction fetched = %b and nPC = %b",$time,inst,PC);
		#2 $display("%g Instruction fetched = %b and nPC = %b",$time,inst,PC);
		#2 $display("%g Instruction fetched = %b and nPC = %b",$time,inst,PC);
	end

initial 
begin	
	#100 $finish;
end


endmodule

a1/a1/Question 2/q2.vcd
$date
	Fri Jan  4 21:30:50 2019
$end
$version
	Icarus Verilog
$end
$timescale
	1s
$end
$scope module q2_tb $end
$var wire 32 ! inst [31:0] $end
$var wire 32 " PC [31:0] $end
$var reg 1 # clk $end
$var reg 1 $ reset $end
$scope module M $end
$var wire 1 # clk $end
$var wire 1 $ reset $end
$var reg 32 % PC [31:0] $end
$var reg 32 & inst [31:0] $end
$var integer 32 ' i [31:0] $end
$upscope $end
$upscope $end
$enddefinitions $end
#0
$dumpvars
b10000000000000000000000000000 '
bx &
b10000000000000000000000 %
0$
0#
b10000000000000000000000 "
bx !
$end
#1
b10000000000000000000100 "
b10000000000000000000100 %
b0 !
b0 &
1#
#2
0#
#3
b10000000000000000001000 "
b10000000000000000001000 %
1#
#4
0#
#5
b10000000000000000000100 "
b10000000000000000000100 %
1#
1$
#6
0#
#7
b10000000000000000001000 "
b10000000000000000001000 %
1#
0$
#8
0#
#9
b10000000000000000001100 "
b10000000000000000001100 %
1#
#10
0#
#11
b10000000000000000010000 "
b10000000000000000010000 %
1#
#12
0#
#13
b10000000000000000010100 "
b10000000000000000010100 %
1#
#14
0#
#15
b10000000000000000011000 "
b10000000000000000011000 %
1#
#16
0#
#17
b10000000000000000011100 "
b10000000000000000011100 %
1#
#18
0#
#19
b10000000000000000100000 "
b10000000000000000100000 %
1#
#20
0#
#21
b10000000000000000100100 "
b10000000000000000100100 %
1#
#22
0#
#23
b10000000000000000101000 "
b10000000000000000101000 %
1#
#24
0#
#25
b10000000000000000101100 "
b10000000000000000101100 %
1#
#26
0#
#27
b10000000000000000110000 "
b10000000000000000110000 %
1#
#28
0#
#29
b10000000000000000110100 "
b10000000000000000110100 %
1#
#30
0#
#31
b10000000000000000111000 "
b10000000000000000111000 %
1#
#32
0#
#33
b10000000000000000111100 "
b10000000000000000111100 %
1#
#34
0#
#35
b10000000000000001000000 "
b10000000000000001000000 %
1#
#36
0#
#37
b10000000000000001000100 "
b10000000000000001000100 %
1#
#38
0#
#39
b10000000000000001001000 "
b10000000000000001001000 %
1#
#40
0#
#41
b10000000000000001001100 "
b10000000000000001001100 %
1#
#42
0#
#43
b10000000000000001010000 "
b10000000000000001010000 %
1#
#44
0#
#45
b10000000000000001010100 "
b10000000000000001010100 %
1#
#46
0#
#47
b10000000000000001011000 "
b10000000000000001011000 %
1#
#48
0#
#49
b10000000000000001011100 "
b10000000000000001011100 %
1#
#50
0#
#51
b10000000000000001100000 "
b10000000000000001100000 %
1#
#52
0#
#53
b10000000000000001100100 "
b10000000000000001100100 %
1#
#54
0#
#55
b10000000000000001101000 "
b10000000000000001101000 %
1#
#56
0#
#57
b10000000000000001101100 "
b10000000000000001101100 %
1#
#58
0#
#59
b10000000000000001110000 "
b10000000000000001110000 %
1#
#60
0#
#61
b10000000000000001110100 "
b10000000000000001110100 %
1#
#62
0#
#63
b10000000000000001111000 "
b10000000000000001111000 %
1#
#64
0#
#65
b10000000000000001111100 "
b10000000000000001111100 %
1#
#66
0#
#67
b10000000000000010000000 "
b10000000000000010000000 %
1#
#68
0#
#69
b10000000000000010000100 "
b10000000000000010000100 %
1#
#70
0#
#71
b10000000000000010001000 "
b10000000000000010001000 %
1#
#72
0#
#73
b10000000000000010001100 "
b10000000000000010001100 %
1#
#74
0#
#75
b10000000000000010010000 "
b10000000000000010010000 %
1#
#76
0#
#77
b10000000000000010010100 "
b10000000000000010010100 %
1#
#78
0#
#79
b10000000000000010011000 "
b10000000000000010011000 %
1#
#80
0#
#81
b10000000000000010011100 "
b10000000000000010011100 %
1#
#82
0#
#83
b10000000000000010100000 "
b10000000000000010100000 %
1#
#84
0#
#85
b10000000000000010100100 "
b10000000000000010100100 %
1#
#86
0#
#87
b10000000000000010101000 "
b10000000000000010101000 %
1#
#88
0#
#89
b10000000000000010101100 "
b10000000000000010101100 %
1#
#90
0#
#91
b10000000000000010110000 "
b10000000000000010110000 %
1#
#92
0#
#93
b10000000000000010110100 "
b10000000000000010110100 %
1#
#94
0#
#95
b10000000000000010111000 "
b10000000000000010111000 %
1#
#96
0#
#97
b10000000000000010111100 "
b10000000000000010111100 %
1#
#98
0#
#99
b10000000000000011000000 "
b10000000000000011000000 %
1#
